arccanet/__init__.py
arccanet/conditionbuilder.py
arccanet/exceptions.py
arccanet/general.py
arccanet/jwt.py
arccanet/parsers.py
arccanet/permissions.py
arccanet/response.py
arccanet/responsebuilder.py
arccanet/serializers.py
arccanet/test.py
arccanet/views.py
arccanet-0.0.7.dist-info/METADATA
arccanet-0.0.7.dist-info/WHEEL
arccanet-0.0.7.dist-info/top_level.txt
arccanet-0.0.7.dist-info/RECORD
