Metadata-Version: 2.1
Name: arccanet
Version: 0.0.7
Summary: Base package for building arccanet backend
Home-page: UNKNOWN
Author: Arcca Tech Team
Author-email: rodrigo.almeida@arcca.io
License: UNKNOWN
Platform: UNKNOWN
Requires-Dist: Django ==3.2.5
Requires-Dist: djangorestframework ==3.12.4
Requires-Dist: djangorestframework-simplejwt ==4.7.2
